{
  "swagger": "2.0",
  "info": {
    "title": "Event Scheduler API",
    "description": "API for creating and managing events",
    "version": "1.0.0"
  },
  "host": "localhost:8080",
  "basePath": "/",
  "schemes": [
    "http"
  ],
  "paths": {
    "/": {
      "post": {
        "description": "",
        "responses": {
          "201": {
            "description": "Created"
          },
          "400": {
            "description": "Bad Request"
          }
        }
      },
      "get": {
        "description": "",
        "responses": {
          "200": {
            "description": "OK"
          },
          "500": {
            "description": "Internal Server Error"
          }
        }
      }
    },
    "/{id}": {
      "get": {
        "description": "",
        "parameters": [
          {
            "name": "id",
            "in": "path",
            "required": true,
            "type": "string"
          }
        ],
        "responses": {
          "200": {
            "description": "OK"
          },
          "404": {
            "description": "Not Found"
          },
          "500": {
            "description": "Internal Server Error"
          }
        }
      }
    }
  },
  "definitions": {
    "Event": {
      "type": "object",
      "properties": {
        "type": {
          "type": "string",
          "example": "object"
        },
        "properties": {
          "type": "object",
          "properties": {
            "title": {
              "type": "object",
              "properties": {
                "type": {
                  "type": "string",
                  "example": "string"
                },
                "example": {
                  "type": "string",
                  "example": "Community Beach Cleanup"
                }
              }
            },
            "description": {
              "type": "object",
              "properties": {
                "type": {
                  "type": "string",
                  "example": "string"
                },
                "example": {
                  "type": "string",
                  "example": "Join us for a Saturday morning to keep the beach clean!"
                }
              }
            },
            "date": {
              "type": "object",
              "properties": {
                "type": {
                  "type": "string",
                  "example": "string"
                },
                "example": {
                  "type": "string",
                  "example": "2025-11-05T09:00:00Z"
                }
              }
            },
            "location": {
              "type": "object",
              "properties": {
                "type": {
                  "type": "string",
                  "example": "string"
                },
                "example": {
                  "type": "string",
                  "example": "Ala Moana Beach Park"
                }
              }
            },
            "category": {
              "type": "object",
              "properties": {
                "type": {
                  "type": "string",
                  "example": "string"
                },
                "example": {
                  "type": "string",
                  "example": "Volunteer"
                }
              }
            },
            "capacity": {
              "type": "object",
              "properties": {
                "type": {
                  "type": "string",
                  "example": "number"
                },
                "example": {
                  "type": "number",
                  "example": 50
                }
              }
            },
            "organizerId": {
              "type": "object",
              "properties": {
                "type": {
                  "type": "string",
                  "example": "string"
                },
                "example": {
                  "type": "string",
                  "example": "652fe97ac51f5b9a278f003c"
                }
              }
            }
          }
        }
      }
    }
  }
}